<PolicySet
 xmlns="urn:oasis:names:tc:xacml:3.0:core:schema:wd-17"
 PolicySetId="P1"
 Version="1.0"
 PolicyCombiningAlgId="urn:oasis:names:tc:xacml:3.0:policy-combining-algorithm:deny-unless-permit">
 <Description>Sample PolicySet</Description>
 <Target />
<Policy xmlns="urn:oasis:names:tc:xacml:3.0:core:schema:wd-17"  PolicyId="NewTicketOnlySupport" RuleCombiningAlgId="urn:oasis:names:tc:xacml:3.0:rule-combining-algorithm:deny-unless-permit" Version="1.0">
   <Target></Target>
   <Rule Effect="Permit" RuleId="NewTicket">
      <Target>
         <AnyOf>
            <AllOf>
               <Match MatchId="urn:oasis:names:tc:xacml:1.0:function:string-equal">
                  <AttributeValue DataType="http://www.w3.org/2001/XMLSchema#string">/new_ticket</AttributeValue>
                  <AttributeDesignator AttributeId="urn:oasis:names:tc:xacml:1.0:resource:resource-id" Category="urn:oasis:names:tc:xacml:3.0:attribute-category:resource" DataType="http://www.w3.org/2001/XMLSchema#string" MustBePresent="true"></AttributeDesignator>
               </Match>
            </AllOf>
         </AnyOf>
         <AnyOf>
            <AllOf>
               <Match MatchId="urn:oasis:names:tc:xacml:1.0:function:string-equal">
                  <AttributeValue DataType="http://www.w3.org/2001/XMLSchema#string">POST</AttributeValue>
                  <AttributeDesignator AttributeId="urn:oasis:names:tc:xacml:1.0:action:action-id" Category="urn:oasis:names:tc:xacml:3.0:attribute-category:action" DataType="http://www.w3.org/2001/XMLSchema#string" MustBePresent="true"></AttributeDesignator>
               </Match>
            </AllOf>
         </AnyOf>
         <AnyOf>
            <AllOf>
               <Match MatchId="urn:oasis:names:tc:xacml:1.0:function:string-equal">
                  <AttributeValue DataType="http://www.w3.org/2001/XMLSchema#string">support</AttributeValue>
                  <AttributeDesignator AttributeId="http://wso2.org/claims/role" Category="urn:oasis:names:tc:xacml:1.0:subject-category:access-subject" DataType="http://www.w3.org/2001/XMLSchema#string" MustBePresent="true"></AttributeDesignator>
               </Match>
            </AllOf>
         </AnyOf>
      </Target>
   </Rule>
</Policy>
</PolicySet>
